{
  "headers": {
    "access-control-allow-origin": "*",
    "cross-origin-opener-policy": "same-origin",
    "via": "http/2 edgeproxy-h",
    "x-amz-cf-pop": "AMS50-C1",
    "x-amz-replication-status": "COMPLETED",
    "content-type": "application/typescript; charset=utf-8",
    "last-modified": "Fri, 25 Mar 2022 13:32:50 GMT",
    "x-amz-version-id": "VcNOI0Pn_ARFXuhusRG8QXPkv7UzEZod",
    "server-timing": "fetchSource;dur=20",
    "x-cache": "Hit from cloudfront",
    "x-content-type-options": "nosniff",
    "vary": "Accept-Encoding, Origin",
    "server": "deno/gcp-europe-west4",
    "cross-origin-embedder-policy": "same-origin",
    "content-security-policy": "default-src 'none'; style-src 'unsafe-inline'; sandbox",
    "content-length": "15290",
    "cache-control": "public, max-age=31536000, immutable",
    "x-frame-options": "DENY",
    "etag": "\"b90529a734d17c89c6ccfdb4a8541404\"",
    "date": "Thu, 23 Nov 2023 22:06:10 GMT",
    "strict-transport-security": "max-age=63072000; includeSubDomains; preload",
    "accept-ranges": "bytes",
    "x-amz-cf-id": "PgLdet8dNghlsV-BPm7tVPOgJxnWIiDBLraBFwUfoAoR3ebxMxVS6Q==",
    "referrer-policy": "strict-origin-when-cross-origin",
    "age": "7309205",
    "cross-origin-resource-policy": "same-origin"
  },
  "url": "https://deno.land/std@0.132.0/node/process.ts",
  "now": {
    "secs_since_epoch": 1708086374,
    "nanos_since_epoch": 369969607
  }
}