{
  "headers": {
    "age": "21410492",
    "cross-origin-opener-policy": "same-origin",
    "cross-origin-resource-policy": "same-origin",
    "last-modified": "Fri, 25 Mar 2022 13:32:50 GMT",
    "cache-control": "public, max-age=31536000, immutable",
    "accept-ranges": "bytes",
    "x-amz-replication-status": "COMPLETED",
    "content-security-policy": "default-src 'none'; style-src 'unsafe-inline'; sandbox",
    "server-timing": "fetchSource;dur=16",
    "cross-origin-embedder-policy": "same-origin",
    "date": "Mon, 12 Jun 2023 19:05:01 GMT",
    "content-type": "application/typescript; charset=utf-8",
    "via": "http/2 edgeproxy-h",
    "x-amz-version-id": "ZFhwuG4aP5SHMm8zbkcjINUJp2jn.ivu",
    "strict-transport-security": "max-age=63072000; includeSubDomains; preload",
    "x-cache": "Hit from cloudfront",
    "content-length": "15189",
    "referrer-policy": "strict-origin-when-cross-origin",
    "access-control-allow-origin": "*",
    "etag": "\"d148e1d8579ce2f302a6849b4cdbad7a\"",
    "vary": "Accept-Encoding, Origin",
    "x-content-type-options": "nosniff",
    "x-amz-cf-pop": "AMS50-C1",
    "x-frame-options": "DENY",
    "server": "deno/gcp-europe-west4",
    "x-amz-cf-id": "5-JlWJBMdzVhEWk3OSvYfkHvnW98OOwY0jz_iwxEfq_hEGDF4Sz3RA=="
  },
  "url": "https://deno.land/std@0.132.0/streams/conversion.ts",
  "now": {
    "secs_since_epoch": 1708007192,
    "nanos_since_epoch": 469554128
  }
}